onecompiler/__init__.py
onecompiler/api/__init__.py
onecompiler/api/async_compiler.py
onecompiler/api/compiler.py
onecompiler/base_errors/LangNotFound.py
onecompiler/base_errors/__init__.py
onecompiler/base_models/__init__.py
onecompiler/base_models/base_compiler.py
onecompiler/data.py
onecompiler/pydantic_models/__init__.py
onecompiler/pydantic_models/lang.py
onecompiler/pydantic_models/response.py
onecompiler/requirements.txt
onecompiler-1.1.6.dist-info/LICENSE
onecompiler-1.1.6.dist-info/METADATA
onecompiler-1.1.6.dist-info/WHEEL
onecompiler-1.1.6.dist-info/RECORD
