Metadata-Version: 2.1
Name: onecompiler
Version: 1.1.6
Summary: 
Home-page: https://github.com/pokedim13/OneCompiler
License: Apache-2.0
Author: pokedim13
Author-email: skinxedovich@vk.com
Requires-Python: >=3.8,<4.0
Classifier: License :: OSI Approved :: Apache Software License
Classifier: Programming Language :: Python :: 3
Classifier: Programming Language :: Python :: 3.8
Classifier: Programming Language :: Python :: 3.9
Classifier: Programming Language :: Python :: 3.10
Classifier: Programming Language :: Python :: 3.11
Requires-Dist: httpx (>=0.24.1,<0.25.0)
Requires-Dist: pydantic (>=1.10.8,<2.0.0)
Project-URL: Repository, https://github.com/pokedim13/OneCompiler
